{"topics": [{"open?": true, "sticky?": true, "link": "https://scratch.mit.edu/discuss/topic/343602/", "title": "The Official List of Rejected Suggestions", "author": "Za-Chary"}, {"open?": true, "sticky?": true, "link": "https://scratch.mit.edu/discuss/topic/611582/", "title": "Scratch Workaround Guide VII", "author": "_nix"}, {"open?": true, "sticky?": true, "link": "https://scratch.mit.edu/discuss/topic/586736/", "title": "The Guide to the Suggestions forum (DON\u2019T suggest here!)", "author": "dertermenter"}, {"open?": true, "sticky?": true, "link": "https://scratch.mit.edu/discuss/topic/657522/", "title": "The 7th Suggestion Directory", "author": "imfh"}, {"open?": false, "sticky?": true, "link": "https://scratch.mit.edu/discuss/topic/675766/", "title": "Why most suggestions fail", "author": "rdococ"}, {"open?": false, "sticky?": true, "link": "https://scratch.mit.edu/discuss/topic/215499/", "title": "Constructive Recommendations On How to Respond to and Make Suggestions!", "author": "Sigton"}, {"open?": false, "sticky?": true, "link": "https://scratch.mit.edu/discuss/topic/285904/", "title": "Guide to Finding Duplicates", "author": "Wahsp"}, {"open?": false, "sticky?": true, "link": "https://scratch.mit.edu/discuss/topic/245/", "title": "How to give helpful suggestions about Scratch: Scratch Design Goals", "author": "Lightnin"}, {"open?": true, "sticky?": false, "link": "https://scratch.mit.edu/discuss/topic/775952/", "title": "Scratch needs to fix the no swearing thing.", "author": "Dinosaurguy77"}, {"open?": true, "sticky?": false, "link": "https://scratch.mit.edu/discuss/topic/319694/", "title": "Automatically fix floating point errors.", "author": "badatprogrammingibe"}, {"open?": true, "sticky?": false, "link": "https://scratch.mit.edu/discuss/topic/469795/", "title": "Stop linking Twitter.", "author": "Futurebot5"}, {"open?": true, "sticky?": false, "link": "https://scratch.mit.edu/discuss/topic/43677/", "title": "Liking/upvoting comments", "author": "Z-zap"}, {"open?": true, "sticky?": false, "link": "https://scratch.mit.edu/discuss/topic/775940/", "title": "Scratch tube / account switching ", "author": "Saifan2014"}, {"open?": true, "sticky?": false, "link": "https://scratch.mit.edu/discuss/topic/107760/", "title": "Changing your featured project title (37-2.5 people support!)", "author": "cwkethan1508"}, {"open?": true, "sticky?": false, "link": "https://scratch.mit.edu/discuss/topic/23873/", "title": "Folders... For Everything.", "author": "crazykidz"}, {"open?": true, "sticky?": false, "link": "https://scratch.mit.edu/discuss/topic/775911/", "title": "Sync Rank with Main Account", "author": "MillionOfficial"}, {"open?": true, "sticky?": false, "link": "https://scratch.mit.edu/discuss/topic/768246/", "title": "Potato Emoji Support.", "author": "BlobbyStudios"}, {"open?": true, "sticky?": false, "link": "https://scratch.mit.edu/discuss/topic/775896/", "title": "Saturation effect", "author": "lionheart921"}, {"open?": false, "sticky?": false, "link": "https://scratch.mit.edu/discuss/topic/775909/", "title": "Hearting suggestion", "author": "birdodeng"}, {"open?": true, "sticky?": false, "link": "https://scratch.mit.edu/discuss/topic/296027/", "title": "[PLEASE DO NOT PROTEST THE PURPLE] An option in account settings to change the site's theme and navigation bar colour", "author": "banana439monkey"}, {"open?": true, "sticky?": false, "link": "https://scratch.mit.edu/discuss/topic/273479/", "title": "Parental controls", "author": "Ed8"}, {"open?": true, "sticky?": false, "link": "https://scratch.mit.edu/discuss/topic/69132/", "title": "Custom c blocks and hat blocks", "author": "dhdguysg"}, {"open?": false, "sticky?": false, "link": "https://scratch.mit.edu/discuss/topic/775938/", "title": "Folders", "author": "bobbyjimmy123"}, {"open?": true, "sticky?": false, "link": "https://scratch.mit.edu/discuss/topic/7073/", "title": "Sprite Folders!", "author": "EdgeGamer"}, {"open?": true, "sticky?": false, "link": "https://scratch.mit.edu/discuss/topic/775847/", "title": "[SOLUTION] Edit/Delete Comments Anywhere", "author": "MillionOfficial"}]}